modoboa_amavis/__init__.py
modoboa_amavis/apps.py
modoboa_amavis/constants.py
modoboa_amavis/dbrouter.py
modoboa_amavis/factories.py
modoboa_amavis/forms.py
modoboa_amavis/handlers.py
modoboa_amavis/lib.py
modoboa_amavis/models.py
modoboa_amavis/modo_extension.py
modoboa_amavis/settings.py
modoboa_amavis/sql_connector.py
modoboa_amavis/sql_email.py
modoboa_amavis/tasks.py
modoboa_amavis/test_runners.py
modoboa_amavis/urls.py
modoboa_amavis/utils.py
modoboa_amavis/views.py
modoboa_amavis/checks/__init__.py
modoboa_amavis/checks/settings_checks.py
modoboa_amavis/locale/cs_CZ/LC_MESSAGES/django.mo
modoboa_amavis/locale/cs_CZ/LC_MESSAGES/django.po
modoboa_amavis/locale/cs_CZ/LC_MESSAGES/djangojs.mo
modoboa_amavis/locale/cs_CZ/LC_MESSAGES/djangojs.po
modoboa_amavis/locale/de/LC_MESSAGES/django.mo
modoboa_amavis/locale/de/LC_MESSAGES/django.po
modoboa_amavis/locale/de/LC_MESSAGES/djangojs.mo
modoboa_amavis/locale/de/LC_MESSAGES/djangojs.po
modoboa_amavis/locale/el_GR/LC_MESSAGES/django.mo
modoboa_amavis/locale/el_GR/LC_MESSAGES/django.po
modoboa_amavis/locale/el_GR/LC_MESSAGES/djangojs.mo
modoboa_amavis/locale/el_GR/LC_MESSAGES/djangojs.po
modoboa_amavis/locale/en/LC_MESSAGES/django.mo
modoboa_amavis/locale/en/LC_MESSAGES/django.po
modoboa_amavis/locale/en/LC_MESSAGES/djangojs.mo
modoboa_amavis/locale/en/LC_MESSAGES/djangojs.po
modoboa_amavis/locale/es/LC_MESSAGES/django.mo
modoboa_amavis/locale/es/LC_MESSAGES/django.po
modoboa_amavis/locale/es/LC_MESSAGES/djangojs.mo
modoboa_amavis/locale/es/LC_MESSAGES/djangojs.po
modoboa_amavis/locale/fr/LC_MESSAGES/django.mo
modoboa_amavis/locale/fr/LC_MESSAGES/django.po
modoboa_amavis/locale/fr/LC_MESSAGES/djangojs.mo
modoboa_amavis/locale/fr/LC_MESSAGES/djangojs.po
modoboa_amavis/locale/it/LC_MESSAGES/django.mo
modoboa_amavis/locale/it/LC_MESSAGES/django.po
modoboa_amavis/locale/it/LC_MESSAGES/djangojs.mo
modoboa_amavis/locale/it/LC_MESSAGES/djangojs.po
modoboa_amavis/locale/nl_NL/LC_MESSAGES/django.mo
modoboa_amavis-1.5.1.dist-info/LICENSE
modoboa_amavis-1.5.1.dist-info/METADATA
modoboa_amavis-1.5.1.dist-info/WHEEL
modoboa_amavis-1.5.1.dist-info/top_level.txt
modoboa_amavis-1.5.1.dist-info/RECORD
