Metadata-Version: 2.1
Name: modoboa-amavis
Version: 1.5.1
Summary: The amavis frontend of Modoboa
Home-page: http://modoboa.org/
Author: Antoine Nguyen
Author-email: tonio@ngyn.org
License: MIT
Keywords: email amavis spamassassin
Classifier: Development Status :: 5 - Production/Stable
Classifier: Environment :: Web Environment
Classifier: Framework :: Django :: 2.2
Classifier: Intended Audience :: System Administrators
Classifier: License :: OSI Approved :: MIT License
Classifier: Operating System :: OS Independent
Classifier: Programming Language :: Python :: 3
Classifier: Programming Language :: Python :: 3.6
Classifier: Programming Language :: Python :: 3.7
Classifier: Programming Language :: Python :: 3.8
Classifier: Topic :: Communications :: Email
Classifier: Topic :: Internet :: WWW/HTTP
License-File: LICENSE
Requires-Dist: chardet
Requires-Dist: html2text
Requires-Dist: idna
